PPINA/CTGN.py
PPINA/__init__.py
PPINA/graph_construction.py
PPINA/protein_degree.py
PPINA-0.1.3.dist-info/LICENSE
PPINA-0.1.3.dist-info/METADATA
PPINA-0.1.3.dist-info/WHEEL
PPINA-0.1.3.dist-info/top_level.txt
PPINA-0.1.3.dist-info/RECORD
