Metadata-Version: 2.1
Name: PPINA
Version: 0.1.3
Summary: PPINA is a python package to analyze Protein Protein Interaction Networks
Home-page: https://github.com/Bassam-Elhamsa/PPINA
Author: Bassam Elhamsa, Mahmoud Nashaat, Ebtehal Mahmoud, Mai Mohamed
Author-email: bassamelhamsa@gmail.com
License: MIT License
Platform: UNKNOWN
Requires-Python: >=3.10
License-File: LICENSE
Requires-Dist: biopython (>=1.81)
Requires-Dist: colorama (>=0.4)
Requires-Dist: matplotlib (>=3.8)
Requires-Dist: networkx (>=3.3)
Requires-Dist: numpy (>=1.24)
